{
  "id": 1,
  "title": "Кинематика",
  "description": "Изучение движения без учета причин, его вызывающих",
  "section": "mechanics",
  "steps": [
    {
      "id": "theory",
      "type": "theory",
      "title": "Теория: Основы кинематики",
      "content": "## Кинематика\n\nКинематика — раздел механики, изучающий движение тел без рассмотрения причин этого движения.\n\n### Основные понятия:\n\n**Материальная точка** — тело, размерами которого можно пренебречь в условиях данной задачи.\n\n**Система отсчета** — совокупность тела отсчета, связанной с ним системы координат и часов.\n\n**Траектория** — линия, по которой движется тело.\n\n### Основные формулы:\n\n**Равномерное движение:**\n- v = const\n- x = x₀ + vt\n\n**Равноускоренное движение:**\n- v = v₀ + at\n- x = x₀ + v₀t + at²/2\n- v² = v₀² + 2a(x - x₀)\n\n### Примеры:\n1. Автомобиль движется со скоростью 60 км/ч\n2. Мяч падает с высоты 20 м"
    },
    {
      "id": "practice",
      "type": "practice",
      "title": "Практика: Решение задач",
      "passScore": 80,
      "questions": [
        {
          "id": "q1",
          "type": "single-choice",
          "question": "Что изучает кинематика?",
          "options": [
            "Движение тел без учета причин",
            "Причины движения тел",
            "Взаимодействие тел",
            "Деформацию тел"
          ],
          "correctAnswer": "Движение тел без учета причин",
          "explanation": "Кинематика изучает только характеристики движения (скорость, ускорение, траекторию), не рассматривая силы."
        },
        {
          "id": "q2",
          "type": "number-input",
          "question": "Автомобиль движется равномерно со скоростью 20 м/с. Какое расстояние он пройдет за 10 секунд? (ответ в метрах)",
          "correctAnswer": 200,
          "explanation": "При равномерном движении: s = vt = 20 × 10 = 200 м"
        },
        {
          "id": "q3",
          "type": "single-choice",
          "question": "Какая формула описывает равноускоренное движение?",
          "options": [
            "x = x₀ + vt",
            "x = x₀ + v₀t + at²/2",
            "v = const",
            "F = ma"
          ],
          "correctAnswer": "x = x₀ + v₀t + at²/2",
          "explanation": "Это основная формула равноускоренного движения, где a ≠ 0."
        },
        {
          "id": "q4",
          "type": "multiple-choice",
          "question": "Выберите характеристики материальной точки:",
          "options": [
            "Имеет массу",
            "Размерами можно пренебречь",
            "Всегда движется",
            "Не имеет формы"
          ],
          "correctAnswer": ["Имеет массу", "Размерами можно пренебречь", "Не имеет формы"],
          "explanation": "Материальная точка — это модель, где размерами тела пренебрегают, но масса сохраняется."
        },
        {
          "id": "q5",
          "type": "formula-match",
          "question": "Сопоставьте формулы с их описанием:",
          "options": [
            "v = v₀ + at → Скорость при равноускоренном движении",
            "x = x₀ + vt → Координата при равномерном движении",
            "v² = v₀² + 2as → Связь скорости и перемещения"
          ],
          "correctAnswer": ["v = v₀ + at → Скорость при равноускоренном движении", "x = x₀ + vt → Координата при равномерном движении", "v² = v₀² + 2as → Связь скорости и перемещения"],
          "explanation": "Каждая формула соответствует определенному типу движения и связывает соответствующие величины."
        }
      ]
    },
    {
      "id": "validation",
      "type": "validation",
      "title": "Валидация практики",
      "passScore": 80
    },
    {
      "id": "control-test",
      "type": "control-test",
      "title": "Контрольный тест",
      "timeLimit": 300,
      "passScore": 70,
      "questions": [
        {
          "id": "ct1",
          "type": "single-choice",
          "question": "Тело движется равноускоренно с начальной скоростью 5 м/с и ускорением 2 м/с². Какова его скорость через 3 секунды?",
          "options": ["8 м/с", "11 м/с", "13 м/с", "15 м/с"],
          "correctAnswer": "11 м/с",
          "explanation": "v = v₀ + at = 5 + 2×3 = 11 м/с"
        },
        {
          "id": "ct2",
          "type": "number-input",
          "question": "Мяч бросили вертикально вверх со скоростью 20 м/с. На какую высоту он поднимется? (g = 10 м/с², ответ в метрах)",
          "correctAnswer": 20,
          "explanation": "h = v₀²/(2g) = 20²/(2×10) = 400/20 = 20 м"
        },
        {
          "id": "ct3",
          "type": "single-choice",
          "question": "Какое движение называется равномерным?",
          "options": [
            "При котором скорость постоянна",
            "При котором ускорение постоянно",
            "При котором траектория прямолинейна",
            "При котором путь равен перемещению"
          ],
          "correctAnswer": "При котором скорость постоянна",
          "explanation": "Равномерное движение характеризуется постоянной скоростью (v = const)."
        },
        {
          "id": "ct4",
          "type": "single-choice",
          "question": "Автомобиль проехал 100 км за 2 часа. Какова его средняя скорость?",
          "options": ["25 км/ч", "50 км/ч", "75 км/ч", "100 км/ч"],
          "correctAnswer": "50 км/ч",
          "explanation": "v = s/t = 100 км / 2 ч = 50 км/ч"
        },
        {
          "id": "ct5",
          "type": "single-choice",
          "question": "При свободном падении тела ускорение равно:",
          "options": ["0 м/с²", "9.8 м/с²", "Зависит от массы", "Зависит от высоты"],
          "correctAnswer": "9.8 м/с²",
          "explanation": "Ускорение свободного падения g ≈ 9.8 м/с² и не зависит от массы тела."
        }
      ]
    }
  ]
}